neau_hpc_utils/__init__.py
neau_hpc_utils/data.py
neau_hpc_utils/data_label.py
neau_hpc_utils/graph.py
neau_hpc_utils/helper.py
neau_hpc_utils/indicator.py
neau_hpc_utils/model.py
neau_hpc_utils-1.5.1.dist-info/LICENSE
neau_hpc_utils-1.5.1.dist-info/METADATA
neau_hpc_utils-1.5.1.dist-info/WHEEL
neau_hpc_utils-1.5.1.dist-info/top_level.txt
neau_hpc_utils-1.5.1.dist-info/RECORD
