Metadata-Version: 2.1
Name: neau-hpc-utils
Version: 1.5.1
Summary: The utils from NEAU HPC Group
Home-page: https://github.com/yuquanF/neau_hpc_utils
Author: yuquanfeng
Author-email: hannerduffly@gmail.com
License: UNKNOWN
Platform: UNKNOWN
Classifier: Programming Language :: Python :: 3
Classifier: License :: OSI Approved :: MIT License
Classifier: Operating System :: OS Independent
Requires-Python: >=3.6
License-File: LICENSE
